src/__init__.py
src/models.py
src/cli/__init__.py
src/cli/__main__.py
src/cli/cli.py
src/cli/print_value.py
src/cli/commands/__init__.py
src/cli/commands/boost.py
src/cli/commands/incoming_boosts.py
src/cli/commands/received_boosts.py
src/cli/commands/sent_boosts.py
src/cli/commands/test.py
src/lnd/__init__.py
src/lnd/lightning_pb2.py
src/lnd/lightning_pb2_grpc.py
src/providers/__init__.py
src/providers/feed_provider.py
src/providers/lightning_provider.py
src/providers/podcast_index_provider.py
src/services/__init__.py
src/services/feed_service.py
src/services/lightning_service.py
src/services/podcast_index_service.py
BoostCLI-0.7.0.dist-info/LICENSE
BoostCLI-0.7.0.dist-info/METADATA
BoostCLI-0.7.0.dist-info/WHEEL
BoostCLI-0.7.0.dist-info/entry_points.txt
BoostCLI-0.7.0.dist-info/top_level.txt
BoostCLI-0.7.0.dist-info/RECORD
